poetry_external_dependencies/__init__.py
poetry_external_dependencies/plugin.py
poetry_external_dependencies-1.2.0.dist-info/METADATA
poetry_external_dependencies-1.2.0.dist-info/WHEEL
poetry_external_dependencies-1.2.0.dist-info/entry_points.txt
poetry_external_dependencies-1.2.0.dist-info/RECORD
