Metadata-Version: 2.1
Name: poetry-external-dependencies
Version: 1.2.0
Summary: 
Author: Jimmy Huguet
Author-email: jimmy.huguet@skillcorner.com
Requires-Python: >=3.11,<4.0
Classifier: Programming Language :: Python :: 3
Classifier: Programming Language :: Python :: 3.11
Requires-Dist: poetry (>=1.2,<=1.6.1)
